sokoenginepy/__init__.py
sokoenginepy/__main__.py
sokoenginepy/game/__init__.py
sokoenginepy/game/base_tessellation.py
sokoenginepy/game/board_cell.py
sokoenginepy/game/board_graph.py
sokoenginepy/game/board_manager.py
sokoenginepy/game/board_state.py
sokoenginepy/game/config.py
sokoenginepy/game/coordinate_helpers.py
sokoenginepy/game/hashed_board_manager.py
sokoenginepy/game/hexoban_tessellation.py
sokoenginepy/game/mover.py
sokoenginepy/game/mover_commands.py
sokoenginepy/game/octoban_tessellation.py
sokoenginepy/game/pusher_step.py
sokoenginepy/game/sokoban_plus.py
sokoenginepy/game/sokoban_tessellation.py
sokoenginepy/game/trioban_tessellation.py
sokoenginepy/game/utilities/__init__.py
sokoenginepy/game/utilities/dict_helpers.py
sokoenginepy/game/utilities/flip_dict.py
sokoenginepy/game/utilities/mover_benchmarks.py
sokoenginepy/io/SOK_format_specification.txt
sokoenginepy/io/__init__.py
sokoenginepy/io/collection.py
sokoenginepy/io/hexoban.py
sokoenginepy/io/octoban.py
sokoenginepy/io/puzzle.py
sokoenginepy/io/puzzle_parsing.py
sokoenginepy/io/rle.py
sokoenginepy/io/snapshot.py
sokoenginepy/io/snapshot_parsing.py
sokoenginepy/io/sok_file_format.py
sokoenginepy/io/sokoban.py
sokoenginepy/io/trioban.py
sokoenginepy/io/utilities.py
sokoenginepy-1.0.3.dist-info/LICENSE
sokoenginepy-1.0.3.dist-info/METADATA
sokoenginepy-1.0.3.dist-info/WHEEL
sokoenginepy-1.0.3.dist-info/top_level.txt
sokoenginepy-1.0.3.dist-info/RECORD
