Metadata-Version: 2.1
Name: sokoenginepy
Version: 1.0.3
Summary: Sokoban and variants game utilities
Author-email: Tomislav Adamic <tomislav.adamic@gmail.com>
License: GNU General Public License v3 or later (GPLv3+)
Project-URL: Homepage, https://github.com/tadams42/sokoenginepy
Project-URL: Source, https://github.com/tadams42/sokoenginepy
Project-URL: Documentation, https://sokoenginepy.readthedocs.io/en/latest/
Keywords: sokoban,hexoban,octoban,trioban,sokoban+,multiban
Platform: any
Classifier: Development Status :: 5 - Production/Stable
Classifier: Intended Audience :: Developers
Classifier: License :: OSI Approved :: GNU General Public License v3 or later (GPLv3+)
Classifier: Programming Language :: Python
Classifier: Programming Language :: Python :: 3.9
Classifier: Programming Language :: Python :: 3.10
Classifier: Programming Language :: Python :: Implementation :: CPython
Classifier: Programming Language :: Python :: 3 :: Only
Classifier: Operating System :: OS Independent
Classifier: Topic :: Software Development :: Libraries :: Python Modules
Classifier: Topic :: Games/Entertainment :: Puzzle Games
Requires-Python: >=3.9
License-File: LICENSE
Requires-Dist: arrow
Requires-Dist: networkx (>2.5)
Requires-Dist: lark (>=1.1.2)
Provides-Extra: dev
Requires-Dist: black ; extra == 'dev'
Requires-Dist: bump2version ; extra == 'dev'
Requires-Dist: ipython ; extra == 'dev'
Requires-Dist: isort ; extra == 'dev'
Requires-Dist: pytest-spec ; extra == 'dev'
Requires-Dist: twine ; extra == 'dev'
Requires-Dist: check-manifest ; extra == 'dev'
Requires-Dist: coverage ; extra == 'dev'
Requires-Dist: factory-boy ; extra == 'dev'
Requires-Dist: faker ; extra == 'dev'
Requires-Dist: pytest (>=3.0.0) ; extra == 'dev'
Requires-Dist: m2r2 ; extra == 'dev'
Requires-Dist: sphinx (>=1.4) ; extra == 'dev'
Requires-Dist: sphinx-rtd-theme ; extra == 'dev'
Provides-Extra: docs
Requires-Dist: m2r2 ; extra == 'docs'
Requires-Dist: sphinx (>=1.4) ; extra == 'docs'
Requires-Dist: sphinx-rtd-theme ; extra == 'docs'
Provides-Extra: tests
Requires-Dist: check-manifest ; extra == 'tests'
Requires-Dist: coverage ; extra == 'tests'
Requires-Dist: factory-boy ; extra == 'tests'
Requires-Dist: faker ; extra == 'tests'
Requires-Dist: pytest (>=3.0.0) ; extra == 'tests'
Requires-Dist: pytest-spec ; extra == 'tests'
